CHANGELOG.txt
LICENSE.txt
MANIFEST.in
README.txt
setup.py
ArtexTest/__init__.py
artextest.egg-info/PKG-INFO
artextest.egg-info/SOURCES.txt
artextest.egg-info/dependency_links.txt
artextest.egg-info/top_level.txt